LICENSE
MANIFEST.in
README
README.md
setup.py
jpeg4py.egg-info/PKG-INFO
jpeg4py.egg-info/SOURCES.txt
jpeg4py.egg-info/dependency_links.txt
jpeg4py.egg-info/requires.txt
jpeg4py.egg-info/top_level.txt
src/jpeg4py/__init__.py
src/jpeg4py/_cffi.py
src/jpeg4py/_py.py
tests/1024.jpg
tests/64.jpg
tests/benchmark.py
tests/test.jpg
tests/test_api.py