Metadata-Version: 1.1
Name: jpeg4py
Version: 0.1.3
Summary: libjpeg-turbo cffi bindings and helper classes
Home-page: https://github.com/ajkxyz/jpeg4py
Author: Samsung Electronics Co.,Ltd.
Author-email: ajk.xyz@gmail.com
License: Simplified BSD
Download-URL: https://github.com/ajkxyz/jpeg4py
Keywords: libjpeg-turbo,jpeg4py
Platform: UNKNOWN
Classifier: Development Status :: 4 - Beta
Classifier: Environment :: Console
Classifier: Intended Audience :: Developers
Classifier: License :: OSI Approved :: BSD License
Classifier: Operating System :: POSIX
Classifier: Programming Language :: Python :: 2.7
Classifier: Programming Language :: Python :: 3.2
Classifier: Programming Language :: Python :: 3.3
Classifier: Programming Language :: Python :: 3.4
Classifier: Programming Language :: Python :: 3.5
Classifier: Programming Language :: Python :: 3.6
Classifier: Topic :: Software Development :: Libraries
